pizone/__init__.py
pizone/controller.py
pizone/discovery.py
pizone/power.py
pizone/version.py
pizone/zone.py
python_izone-1.2.9.dist-info/METADATA
python_izone-1.2.9.dist-info/WHEEL
python_izone-1.2.9.dist-info/licence.txt
python_izone-1.2.9.dist-info/top_level.txt
python_izone-1.2.9.dist-info/RECORD
