Metadata-Version: 2.1
Name: python-izone
Version: 1.2.9
Summary: A python interface to the iZone airconditioner controller
Home-page: https://github.com/Swamp-Ig/pizone
Author: Penny Wood
Author-email: pypl@ninjateaparty.com
Keywords: iZone,IoT
Classifier: Development Status :: 5 - Production/Stable
Classifier: Intended Audience :: Developers
Classifier: Programming Language :: Python :: 3.9
Classifier: License :: OSI Approved :: GNU General Public License v3 or later (GPLv3+)
Classifier: Operating System :: OS Independent
Classifier: Topic :: Home Automation
Classifier: Topic :: System :: Hardware
Requires-Python: >=3.9
License-File: licence.txt
Requires-Dist: aiohttp (>=3.4)
Requires-Dist: netifaces
Requires-Dist: async-timeout
Provides-Extra: all
Requires-Dist: pytest (>=6.2.2) ; extra == 'all'
Requires-Dist: pytest-aio ; extra == 'all'
Requires-Dist: pytest-aiohttp ; extra == 'all'
Provides-Extra: test
Requires-Dist: pytest (>=6.2.2) ; extra == 'test'
Requires-Dist: pytest-aio ; extra == 'test'
Requires-Dist: pytest-aiohttp ; extra == 'test'
